[
  {
    "airport": {
      "identity": 3,
      "labels": [
        "Airport"
      ],
      "properties": {
        "name": "SAT"
      }
    },
    "COUNT(flight)": 1
  },
  {
    "airport": {
      "identity": 6,
      "labels": [
        "Airport"
      ],
      "properties": {
        "name": "FLL"
      }
    },
    "COUNT(flight)": 1
  },
  {
    "airport": {
      "identity": 9,
      "labels": [
        "Airport"
      ],
      "properties": {
        "name": "KOA"
      }
    },
    "COUNT(flight)": 1
  },
  {
    "airport": {
      "identity": 13,
      "labels": [
        "Airport"
      ],
      "properties": {
        "name": "SMF"
      }
    },
    "COUNT(flight)": 1
  },
  {
    "airport": {
      "identity": 14,
      "labels": [
        "Airport"
      ],
      "properties": {
        "name": "RIC"
      }
    },
    "COUNT(flight)": 1
  },
  {
    "airport": {
      "identity": 15,
      "labels": [
        "Airport"
      ],
      "properties": {
        "name": "IND"
      }
    },
    "COUNT(flight)": 1
  },
  {
    "airport": {
      "identity": 20,
      "labels": [
        "Airport"
      ],
      "properties": {
        "name": "MCI"
      }
    },
    "COUNT(flight)": 1
  },
  {
    "airport": {
      "identity": 21,
      "labels": [
        "Airport"
      ],
      "properties": {
        "name": "MSN"
      }
    },
    "COUNT(flight)": 1
  },
  {
    "airport": {
      "identity": 30,
      "labels": [
        "Airport"
      ],
      "properties": {
        "name": "BIL"
      }
    },
    "COUNT(flight)": 1
  },
  {
    "airport": {
      "identity": 32,
      "labels": [
        "Airport"
      ],
      "properties": {
        "name": "ROC"
      }
    },
    "COUNT(flight)": 1
  },
  {
    "airport": {
      "identity": 33,
      "labels": [
        "Airport"
      ],
      "properties": {
        "name": "CLT"
      }
    },
    "COUNT(flight)": 1
  },
  {
    "airport": {
      "identity": 34,
      "labels": [
        "Airport"
      ],
      "properties": {
        "name": "DCA"
      }
    },
    "COUNT(flight)": 1
  },
  {
    "airport": {
      "identity": 38,
      "labels": [
        "Airport"
      ],
      "properties": {
        "name": "PBI"
      }
    },
    "COUNT(flight)": 1
  },
  {
    "airport": {
      "identity": 39,
      "labels": [
        "Airport"
      ],
      "properties": {
        "name": "MIA"
      }
    },
    "COUNT(flight)": 1
  },
  {
    "airport": {
      "identity": 45,
      "labels": [
        "Airport"
      ],
      "properties": {
        "name": "MOB"
      }
    },
    "COUNT(flight)": 1
  },
  {
    "airport": {
      "identity": 22,
      "labels": [
        "Airport"
      ],
      "properties": {
        "name": "SNA"
      }
    },
    "COUNT(flight)": 2
  },
  {
    "airport": {
      "identity": 25,
      "labels": [
        "Airport"
      ],
      "properties": {
        "name": "LAS"
      }
    },
    "COUNT(flight)": 2
  },
  {
    "airport": {
      "identity": 26,
      "labels": [
        "Airport"
      ],
      "properties": {
        "name": "ATL"
      }
    },
    "COUNT(flight)": 2
  },
  {
    "airport": {
      "identity": 27,
      "labels": [
        "Airport"
      ],
      "properties": {
        "name": "CMH"
      }
    },
    "COUNT(flight)": 2
  },
  {
    "airport": {
      "identity": 28,
      "labels": [
        "Airport"
      ],
      "properties": {
        "name": "SJC"
      }
    },
    "COUNT(flight)": 2
  },
  {
    "airport": {
      "identity": 31,
      "labels": [
        "Airport"
      ],
      "properties": {
        "name": "LGA"
      }
    },
    "COUNT(flight)": 2
  },
  {
    "airport": {
      "identity": 42,
      "labels": [
        "Airport"
      ],
      "properties": {
        "name": "TUS"
      }
    },
    "COUNT(flight)": 2
  },
  {
    "airport": {
      "identity": 0,
      "labels": [
        "Airport"
      ],
      "properties": {
        "name": "SEA"
      }
    },
    "COUNT(flight)": 3
  },
  {
    "airport": {
      "identity": 29,
      "labels": [
        "Airport"
      ],
      "properties": {
        "name": "PHX"
      }
    },
    "COUNT(flight)": 3
  },
  {
    "airport": {
      "identity": 46,
      "labels": [
        "Airport"
      ],
      "properties": {
        "name": "SBN"
      }
    },
    "COUNT(flight)": 3
  },
  {
    "airport": {
      "identity": 4,
      "labels": [
        "Airport"
      ],
      "properties": {
        "name": "MCO"
      }
    },
    "COUNT(flight)": 4
  },
  {
    "airport": {
      "identity": 10,
      "labels": [
        "Airport"
      ],
      "properties": {
        "name": "PDX"
      }
    },
    "COUNT(flight)": 4
  },
  {
    "airport": {
      "identity": 16,
      "labels": [
        "Airport"
      ],
      "properties": {
        "name": "BOS"
      }
    },
    "COUNT(flight)": 4
  },
  {
    "airport": {
      "identity": 18,
      "labels": [
        "Airport"
      ],
      "properties": {
        "name": "DFW"
      }
    },
    "COUNT(flight)": 4
  },
  {
    "airport": {
      "identity": 24,
      "labels": [
        "Airport"
      ],
      "properties": {
        "name": "SAN"
      }
    },
    "COUNT(flight)": 4
  },
  {
    "airport": {
      "identity": 35,
      "labels": [
        "Airport"
      ],
      "properties": {
        "name": "BHM"
      }
    },
    "COUNT(flight)": 4
  },
  {
    "airport": {
      "identity": 37,
      "labels": [
        "Airport"
      ],
      "properties": {
        "name": "CVG"
      }
    },
    "COUNT(flight)": 4
  },
  {
    "airport": {
      "identity": 40,
      "labels": [
        "Airport"
      ],
      "properties": {
        "name": "ABQ"
      }
    },
    "COUNT(flight)": 4
  },
  {
    "airport": {
      "identity": 41,
      "labels": [
        "Airport"
      ],
      "properties": {
        "name": "FAT"
      }
    },
    "COUNT(flight)": 4
  },
  {
    "airport": {
      "identity": 43,
      "labels": [
        "Airport"
      ],
      "properties": {
        "name": "DLH"
      }
    },
    "COUNT(flight)": 4
  },
  {
    "airport": {
      "identity": 19,
      "labels": [
        "Airport"
      ],
      "properties": {
        "name": "SLC"
      }
    },
    "COUNT(flight)": 5
  },
  {
    "airport": {
      "identity": 23,
      "labels": [
        "Airport"
      ],
      "properties": {
        "name": "HNL"
      }
    },
    "COUNT(flight)": 5
  },
  {
    "airport": {
      "identity": 44,
      "labels": [
        "Airport"
      ],
      "properties": {
        "name": "FSD"
      }
    },
    "COUNT(flight)": 5
  },
  {
    "airport": {
      "identity": 1,
      "labels": [
        "Airport"
      ],
      "properties": {
        "name": "EWR"
      }
    },
    "COUNT(flight)": 7
  },
  {
    "airport": {
      "identity": 49,
      "labels": [
        "Airport"
      ],
      "properties": {
        "name": "MOT"
      }
    },
    "COUNT(flight)": 8
  },
  {
    "airport": {
      "identity": 8,
      "labels": [
        "Airport"
      ],
      "properties": {
        "name": "MSP"
      }
    },
    "COUNT(flight)": 9
  },
  {
    "airport": {
      "identity": 12,
      "labels": [
        "Airport"
      ],
      "properties": {
        "name": "IAD"
      }
    },
    "COUNT(flight)": 12
  },
  {
    "airport": {
      "identity": 36,
      "labels": [
        "Airport"
      ],
      "properties": {
        "name": "BNA"
      }
    },
    "COUNT(flight)": 12
  },
  {
    "airport": {
      "identity": 47,
      "labels": [
        "Airport"
      ],
      "properties": {
        "name": "AZO"
      }
    },
    "COUNT(flight)": 13
  },
  {
    "airport": {
      "identity": 11,
      "labels": [
        "Airport"
      ],
      "properties": {
        "name": "SFO"
      }
    },
    "COUNT(flight)": 14
  },
  {
    "airport": {
      "identity": 17,
      "labels": [
        "Airport"
      ],
      "properties": {
        "name": "DEN"
      }
    },
    "COUNT(flight)": 18
  },
  {
    "airport": {
      "identity": 5,
      "labels": [
        "Airport"
      ],
      "properties": {
        "name": "LAX"
      }
    },
    "COUNT(flight)": 22
  },
  {
    "airport": {
      "identity": 2,
      "labels": [
        "Airport"
      ],
      "properties": {
        "name": "IAH"
      }
    },
    "COUNT(flight)": 23
  },
  {
    "airport": {
      "identity": 48,
      "labels": [
        "Airport"
      ],
      "properties": {
        "name": "DTW"
      }
    },
    "COUNT(flight)": 25
  },
  {
    "airport": {
      "identity": 7,
      "labels": [
        "Airport"
      ],
      "properties": {
        "name": "ORD"
      }
    },
    "COUNT(flight)": 48
  }
]